flake8_literal/__init__.py
flake8_literal/checker.py
flake8_literal/quote_checker.py
flake8_literal/raw_checker.py
flake8_literal-1.5.0.dist-info/METADATA
flake8_literal-1.5.0.dist-info/WHEEL
flake8_literal-1.5.0.dist-info/entry_points.txt
flake8_literal-1.5.0.dist-info/top_level.txt
flake8_literal-1.5.0.dist-info/RECORD
